[
{"url": "https://e-seimas.lrs.lt/portal/legalAct/lt/TAP/fff58300a7d411efaae6a4c601761171", "Date": "2024-11-21", "title": "Dėl Lietuvos Respublikos Seimo 2024 m. lapkričio 19 d. nutarimo Nr. XV-14 „Dėl Lietuvos Respublikos Seimo komitetų narių skaičiaus", "related_documents": [], "files": []},
{"url": "https://e-seimas.lrs.lt/portal/legalAct/lt/TAP/325923b0a7d511efaae6a4c601761171", "Date": "2024-11-21", "title": "Dėl Lietuvos Respublikos Seimo 2024 m. lapkričio 19 d. nutarimo Nr. XV-15 „Dėl Lietuvos Respublikos Seimo komitetų sudėties patvirtinimo", "related_documents": [], "files": []},
{"url": "https://e-seimas.lrs.lt/portal/legalAct/lt/TAP/c5dc8190a7d511efaae6a4c601761171", "Date": "2024-11-21", "title": "Dėl Lietuvos Respublikos Seimo komitetų pirmininkų ir jų pavaduotojų patvirtinimo", "related_documents": [], "files": []},
{"url": "https://e-seimas.lrs.lt/portal/legalAct/lt/TAP/98aba6c0a71611efaae6a4c601761171", "Date": "2024-11-20", "title": "Administracinių nusižengimų kodekso 486 straipsnio pakeitimo įstatymo projektas", "related_documents": [], "files": []},
{"url": "https://e-seimas.lrs.lt/portal/legalAct/lt/TAP/d4ac5810a7d211efaae6a4c601761171", "Date": "2024-11-21", "title": "Dėl Lietuvos Respublikos Seimo statuto Nr. I-399 44-2 straipsnio pakeitimo", "related_documents": [], "files": []}
]